[
  { "date": "2025.09", "title": "NPO設立を考える", "desc": "会津で何かできないか。まずは仲間を集めるところから始まった。" },
  { "date": "2025.12", "title": "NPO設立認証", "desc": "正式にNPO法人として認証を受けた。ここからがスタート。" },
  { "date": "2025.12", "title": "市民協働事業スタート", "desc": "会津若松市役所との協働プロジェクトが動き出した。" },
  { "date": "2025.12", "title": "Webサイト公開", "desc": "活動を知ってもらうために、このサイトを立ち上げた。" },
  { "date": "2026.01", "title": "メンバー16人に", "desc": "少しずつ、仲間が増えてきた。" },
  { "date": "2026.02", "title": "ビニールハウス再生", "desc": "木を切り、草を刈り、ハウスの内外をきれいにした。再生への第一歩。" }
]
